offline_stenographer/__init__.py
offline_stenographer/constants.py
offline_stenographer/gui/__init__.py
offline_stenographer/gui/app.py
offline_stenographer/gui/widgets/__init__.py
offline_stenographer/gui/widgets/about_dialog.py
offline_stenographer/gui/widgets/configuration_dialog.py
offline_stenographer/gui/widgets/control_frame.py
offline_stenographer/gui/widgets/export_dialog.py
offline_stenographer/gui/widgets/file_selection_frame.py
offline_stenographer/gui/widgets/log_frame.py
offline_stenographer/gui/widgets/menu_bar.py
offline_stenographer/gui/widgets/output_format_frame.py
offline_stenographer/gui/widgets/progress_frame.py
offline_stenographer/main.py
offline_stenographer/processing/__init__.py
offline_stenographer/processing/config_manager.py
offline_stenographer/processing/export_manager.py
offline_stenographer/processing/formatters.py
offline_stenographer/processing/transcription_service.py
offline_stenographer/processing/type_hints.py
offline_stenographer/processing/video_processor.py
offline_stenographer/utils/__init__.py
offline_stenographer/utils/url_utils.py
offline_stenographer-0.1.0.dist-info/METADATA
offline_stenographer-0.1.0.dist-info/WHEEL
offline_stenographer-0.1.0.dist-info/entry_points.txt
offline_stenographer-0.1.0.dist-info/licenses/LICENSE
offline_stenographer-0.1.0.dist-info/RECORD
