Metadata-Version: 2.4
Name: offline-stenographer
Version: 0.1.0
Summary: A GUI application for creating transcripts from video files using WhisperX
License-File: LICENSE
Author: Aleksandr Sinitca
Author-email: your-email@example.com
Requires-Python: >=3.12,<4.0
Classifier: Programming Language :: Python :: 3
Classifier: Programming Language :: Python :: 3.12
Classifier: Programming Language :: Python :: 3.13
Classifier: Programming Language :: Python :: 3.14
Requires-Dist: Pillow (>=10.0.0)
Requires-Dist: docker (>=6.1.0)
Requires-Dist: python-docx (>=0.8.11)
